pseek/__init__.py
pseek/cli.py
pseek/extensions
pseek/parser.py
pseek/searcher.py
pseek/utils.py
pseek-2.5.4.dist-info/licenses/LICENSE
pseek-2.5.4.dist-info/METADATA
pseek-2.5.4.dist-info/WHEEL
pseek-2.5.4.dist-info/entry_points.txt
pseek-2.5.4.dist-info/top_level.txt
pseek-2.5.4.dist-info/RECORD
