Metadata-Version: 2.4
Name: pseek
Version: 2.5.4
Summary: Pseek is a Python library to search files, folders, and text
Author-email: Arian <ariannasiri86@gmail.com>
License-Expression: MIT
Project-URL: Homepage, https://github.com/ArianN8610/pysearch
Requires-Python: >=3.6
License-File: LICENSE
Requires-Dist: click==8.1.8
Requires-Dist: lark==1.2.2
Requires-Dist: py7zr==1.0.0
Requires-Dist: rarfile==4.2
Requires-Dist: rapidfuzz==3.13.0
Dynamic: license-file
